{
  "schema_version": 1,
  "mission_id": "M-167",
  "state": "open",
  "pr_number": 16,
  "pr_url": "https://github.com/Cryptoteep/promptkit/pull/16",
  "pr_head_oid": "85a8363a75f70d80d837205f89f9716b3caf179d",
  "base_branch": "main",
  "head_drift": false,
  "ci_state": "pending",
  "merge_commit_oid": null,
  "review_decision": null,
  "decision_url": null,
  "opened_at": "2026-07-16T22:49:33Z",
  "closed_at": null,
  "updated_at": "2026-07-16T22:49:33Z",
  "observed_at": "2026-07-16T22:49:35.031Z",
  "correction_note": null,
  "scope_note": "The receipt proves the declared automated checks only; maintainer review and merge remain independent human decisions.",
  "bundle_digest": "sha256:f230958e2caea8d6759d90a00300964538d314c9c16842b4cd12ee42d5eadcca",
  "attestation_uri": "https://github.com/northset-oss/verification-pilot/releases/download/run-record-M-167-f230958e2cae/run-record-M-167-f230958e2cae.tar.gz",
  "release_asset_sha256": "sha256:e0cdd9f4a40597eb00d1091b6dd908083069116734a49e2de127c0ca73042544",
  "attestation_verified_at": "2026-07-16T22:49:26.832Z",
  "pr_disclosure": {
    "schema_version": 1,
    "required": true,
    "mode": "pr_body",
    "canonical_url": "https://northset-oss.github.io/verification-pilot/receipts/M-167/",
    "verified_at": "2026-07-16T22:49:35.031Z"
  }
}
