{
  "schema_version": 1,
  "mission_id": "M-161",
  "state": "prepared",
  "pr_number": null,
  "pr_url": null,
  "pr_head_oid": null,
  "base_branch": null,
  "head_drift": false,
  "ci_state": null,
  "merge_commit_oid": null,
  "review_decision": null,
  "decision_url": null,
  "opened_at": null,
  "closed_at": null,
  "updated_at": null,
  "observed_at": null,
  "correction_note": null,
  "scope_note": null,
  "attestation_uri": null,
  "bundle_digest": "sha256:d0d9dfc467c2718a53a961c2b686d639503b7ca63f3615b8895fb126196e0634",
  "release_asset_sha256": null,
  "attestation_verified_at": null
}
